python_watcher_metering_drivers-0.21.0.dist-info/entry_points.txt
python_watcher_metering_drivers-0.21.0.dist-info/DESCRIPTION.rst
python_watcher_metering_drivers-0.21.0.dist-info/top_level.txt
python_watcher_metering_drivers-0.21.0.dist-info/RECORD
python_watcher_metering_drivers-0.21.0.dist-info/METADATA
python_watcher_metering_drivers-0.21.0.dist-info/pbr.json
python_watcher_metering_drivers-0.21.0.dist-info/metadata.json
python_watcher_metering_drivers-0.21.0.dist-info/WHEEL
python_watcher_metering_drivers-0.21.0.data/data/etc/watcher-metering/watcher-metering-drivers.conf.sample
watcher_metering_drivers/swap.py
watcher_metering_drivers/memory.py
watcher_metering_drivers/disk.py
watcher_metering_drivers/instance_cpu.py
watcher_metering_drivers/opts.py
watcher_metering_drivers/cpu.py
watcher_metering_drivers/__init__.py
watcher_metering_drivers/doc.py
watcher_metering_drivers/pdu.py
watcher_metering_drivers/version.py
watcher_metering_drivers/tests/test_disk.py
watcher_metering_drivers/tests/test_pdu.py
watcher_metering_drivers/tests/test_register.py
watcher_metering_drivers/tests/test_memory.py
watcher_metering_drivers/tests/test_cpu.py
watcher_metering_drivers/tests/test_instance_cpu.py
watcher_metering_drivers/tests/test_swap.py
watcher_metering_drivers/tests/__init__.py
watcher_metering_drivers/tests/base.py
watcher_metering_drivers/wrappers/host_monitoring.py
watcher_metering_drivers/wrappers/cpu.py
watcher_metering_drivers/wrappers/pdu_raritan.py
watcher_metering_drivers/wrappers/__init__.py
watcher_metering_drivers/wrappers/virt/inspector.py
watcher_metering_drivers/wrappers/virt/util.py
watcher_metering_drivers/wrappers/virt/__init__.py
watcher_metering_drivers/wrappers/virt/instance/__init__.py
watcher_metering_drivers/wrappers/virt/instance/base.py
